sardana_pmac/__init__.py
sardana_pmac/_version.py
sardana_pmac/ctrl/AlbaLtpTurboPmacCtrl.py
sardana_pmac/ctrl/PmacCtrl.py
sardana_pmac/ctrl/PmacLTPCtrl.py
sardana_pmac/ctrl/TurboPmacCtrl.py
sardana_pmac/ctrl/__init__.py
sardana_pmac/macro/__init__.py
sardana_pmac-0.4.0.dist-info/licenses/LICENSE
sardana_pmac-0.4.0.dist-info/METADATA
sardana_pmac-0.4.0.dist-info/WHEEL
sardana_pmac-0.4.0.dist-info/top_level.txt
sardana_pmac-0.4.0.dist-info/RECORD
