Metadata-Version: 2.4
Name: sardana-pmac
Version: 0.4.0
Summary: Pmac Sardana plugins (controllers, macros, tools)
License-Expression: GPL-3.0-or-later
Project-URL: Source, https://gitlab.com/sardana-org/sardana-pmac
Requires-Python: >=3.9
License-File: LICENSE
Requires-Dist: sardana
Dynamic: license-file
